pymymeter/__init__.py
pymymeter/const.py
pymymeter/exceptions.py
pymymeter/pymymeter.py
pymymeter-0.0.11.dist-info/LICENSE
pymymeter-0.0.11.dist-info/METADATA
pymymeter-0.0.11.dist-info/WHEEL
pymymeter-0.0.11.dist-info/top_level.txt
pymymeter-0.0.11.dist-info/RECORD
