Metadata-Version: 2.1
Name: pymymeter
Version: 0.0.11
Summary: A python library for getting historical utilities usage for mymeter.
Author-email: Samuel Geist <samuel.geist@gmail.com>
License: MIT License
Project-URL: Homepage, https://github.com/myztillx/mymeter
Project-URL: Bug Tracker, https://github.com/myztillx/mymeter/issues
Requires-Python: >=3.9
License-File: LICENSE
Requires-Dist: aiohttp >=3.8
